LICENSE
MANIFEST.in
README.rst
setup.cfg
setup.py
sirdjango/__init__.py
sirdjango/blocks.py
sirdjango/conf.py
sirdjango/fields.py
sirdjango/markdown.py
sirdjango/models.py
sirdjango/render.py
sirdjango/widgets.py
sirdjango.egg-info/PKG-INFO
sirdjango.egg-info/SOURCES.txt
sirdjango.egg-info/dependency_links.txt
sirdjango.egg-info/not-zip-safe
sirdjango.egg-info/requires.txt
sirdjango.egg-info/top_level.txt
sirdjango/static/sirdjango/css/sir-trevor-icons.css
sirdjango/static/sirdjango/css/sir-trevor.css
sirdjango/static/sirdjango/js/eventable.js
sirdjango/static/sirdjango/js/jquery.js
sirdjango/static/sirdjango/js/sir-trevor.js
sirdjango/static/sirdjango/js/underscore.js