Metadata-Version: 1.1
Name: sirdjango
Version: 0.1.9
Summary: Sir Trevor integration with Django
Home-page: https://bitbucket.org/takeflight/sirdjango
Author: Tim Heap
Author-email: tim@takeflight.com.au
License: BSD License
Platform: UNKNOWN
Classifier: Environment :: Web Environment
Classifier: Intended Audience :: Developers
Classifier: Operating System :: OS Independent
Classifier: Programming Language :: Python
Classifier: Programming Language :: Python :: 2.6
Classifier: Programming Language :: Python :: 2.7
Classifier: Framework :: Django
Classifier: License :: OSI Approved :: BSD License
